unipark/__init__.py
unipark/config.py
unipark/requests.py
unipark/version.py
unipark/cli/__init__.py
unipark/mvc/__init__.py
unipark/mvc/command.py
unipark/mvc/facade.py
unipark/mvc/mediator.py
unipark/mvc/observer.py
unipark/mvc/proxy.py
unipark/utils/__init__.py
unipark/utils/log.py
unipark/utils/translation.py
unipark-0.0.6.dist-info/METADATA
unipark-0.0.6.dist-info/WHEEL
unipark-0.0.6.dist-info/entry_points.txt
unipark-0.0.6.dist-info/top_level.txt
unipark-0.0.6.dist-info/RECORD
