Metadata-Version: 2.1
Name: unipark
Version: 0.0.6
Summary: Common library of UniPark
Home-page: https://www.unipark.io
Author: Park Lam
Author-email: lqmonline@gmail.com
License: Apache2.0
Platform: UNKNOWN
Requires-Dist: six==1.16.0
Requires-Dist: cffi==1.15.1
Requires-Dist: click==8.1.3
Requires-Dist: cryptography==40.0.1
Requires-Dist: pycparser==2.21
Requires-Dist: python-decouple==3.8
Requires-Dist: requests==2.31.0
